watchmen_storage_rds/__init__.py
watchmen_storage_rds/dbscript_builder.py
watchmen_storage_rds/ext_types.py
watchmen_storage_rds/settings.py
watchmen_storage_rds/sort_build.py
watchmen_storage_rds/storage_rds.py
watchmen_storage_rds/table_defs.py
watchmen_storage_rds/table_defs_helper.py
watchmen_storage_rds/table_reflector.py
watchmen_storage_rds/topic_data_storage_rds.py
watchmen_storage_rds/topic_table_generate.py
watchmen_storage_rds/types.py
watchmen_storage_rds-18.0.1.dist-info/METADATA
watchmen_storage_rds-18.0.1.dist-info/WHEEL
watchmen_storage_rds-18.0.1.dist-info/RECORD
