Metadata-Version: 2.4
Name: watchmen-storage-rds
Version: 18.0.1
Summary: 
License: MIT
Author: botlikes
Author-email: 75356972+botlikes456@users.noreply.github.com
Requires-Python: >=3.12,<3.13
Classifier: License :: OSI Approved :: MIT License
Classifier: Programming Language :: Python :: 3
Classifier: Programming Language :: Python :: 3.12
Requires-Dist: SQLAlchemy (>=2.0.35,<2.1.0)
Requires-Dist: watchmen-storage (==18.0.1)
